design.v
module datapath(
  input clk,
  input rstn,
  output reg [15:0] bus
);
  reg [2:0] DR;
  reg [2:0] SR1;
  wire [2:0] SR2;
  wire [15:0] ALUA;
  wire [15:0] ALUB;

  reg R;
  reg BEN;
  reg [2:0] CC;
  reg [15:0] IR;

  reg LD_BEN;
  reg LD_MAR;
  reg LD_MDR;
  reg LD_IR;
  reg LD_PC;
  reg LD_REG;
  reg LD_CC;
  reg GateMARMUX;
  reg GateMDR;
  reg GateALU;
  reg GatePC;
  reg MARMUX;
  reg [1:0] PCMUX;
  reg ADDR1MUX;
  reg [1:0] ADDR2MUX;
  reg [1:0] DRMUX;
  reg [1:0] SR1MUX;
  reg [1:0] ALUK;
  reg MIO_EN;
  reg R_W;

  reg [15:0] SR1OUT;
  reg [15:0] SR2OUT;
  reg [15:0] ALUout;
  reg [15:0] MARMUXout;
  reg [15:0] PCout;

  reg [15:0] MARout;
  reg [15:0] MDRout;

  reg [15:0] DRIN;
  

  regfile regfile1 (clk, rstn, DRIN, DR, SR1, SR2, LD_REG, SR1OUT, SR2OUT);

  alu alu1 (ALUA, ALUB, ALUK, ALUout);
  pc_mar_muxes pc_mar_muxes1 (clk, rstn, MARMUX, ADDR2MUX, ADDR1MUX, PCMUX, LD_PC, IR, SR1OUT, bus, MARMUXout, PCout);
  control_unit control_unit1 (clk, rstn, R, BEN, IR, LD_BEN, LD_MAR, LD_MDR, LD_IR, LD_PC, LD_REG, LD_CC, GateMARMUX, GateMDR,
  GateALU, GatePC, MARMUX, PCMUX, ADDR1MUX, ADDR2MUX, DRMUX, SR1MUX, ALUK, MIO_EN, R_W);
  BEN_CC BEN_CC1 (clk, rstn, bus, IR, LD_BEN, LD_CC, BEN, CC);
  datapath_memory datapath_memory1 (clk, rstn, bus, LD_MAR, LD_MDR, MIO_EN, R_W, R, MARout, MDRout);

  always @(*) begin
    case (DRMUX)
      2'b00: DR = IR[11:9];
      2'b01: DR = 3'b111;
      2'b10: DR = 3'b110;
      2'b11: DR = 3'bxxx;
    endcase
    case (SR1MUX)
      2'b00: SR1 = IR[11:9];
      2'b01: SR1 = IR[8:6];
      2'b10: SR1 = 3'b110;
      2'b11: SR1 = 3'bxxx;
    endcase
    case ({GatePC, GateMARMUX, GateALU, GateMDR})
       4'b1000: bus = PCout;
       4'b0100: bus = MARMUXout;
       4'b0010: bus = ALUout;
       4'b0001: bus = MDRout;
    endcase
  end

  always @(posedge clk) begin
    if (!rstn) begin
      IR <= 16'b0;
    end
    else begin
      if (LD_IR) IR <= bus;
      else IR <= IR;
    end
  end

  assign DRIN = bus;
  assign SR2 = IR[2:0];
  assign ALUA = SR1OUT;
  assign ALUB = (IR[5]) ? {{27{IR[4]}}, IR[4:0]} : SR2OUT;
endmodule

module control_unit (
  input clk,
  input rstn,
  input R,
  input BEN,
  input reg [15:0] IR,

  output reg LD_BEN,
  output reg LD_MAR,
  output reg LD_MDR,
  output reg LD_IR,
  output reg LD_PC,
  output reg LD_REG,
  output reg LD_CC,
  output reg GateMARMUX,
  output reg GateMDR,
  output reg GateALU,
  output reg GatePC,
  output reg MARMUX,
  output reg [1:0] PCMUX,
  output reg ADDR1MUX,
  output reg [1:0] ADDR2MUX,
  output reg [1:0] DRMUX,
  output reg [1:0] SR1MUX,
  output reg [1:0] ALUK,
  output reg MIO_EN,
  output reg R_W
);

  typedef enum {ADD, AND, NOT, TRAP, TRAP_MEM, TRAP_SET_PC, LEA, LD, LD_MEM, LD_SET_DR, LDR, LDI, LDI_MEM, LDI_SET_MAR, ST, ST_SET_MDR, ST_MEM, STR, STI, STI_MEM, STI_SET_MAR,
  JSR_CHECK, JSR, JSRR, JMP, BR_CHECK, BR, FETCH, FETCH_MEM, FETCH_SET_IR, DECODE, RESET, HALT} microsequencer_state;

  microsequencer_state state;
  microsequencer_state state_next;

  always @(*) begin
    // Default Values for Control Signals.
    LD_BEN = 1'b0;
    LD_MAR = 1'b0;
    LD_MDR = 1'b0;
    LD_IR = 1'b0;
    LD_PC = 1'b0;
    LD_REG = 1'b0;
    LD_CC=  1'b0;
    GateMARMUX = 1'b0;
    GateMDR = 1'b0;
    GateALU = 1'b0;
    GatePC = 1'b0;
    MARMUX  = 1'bx;
    PCMUX = 2'bxx;
    ADDR1MUX = 1'bx;
    ADDR2MUX = 2'bxx;
    DRMUX = 2'bxx;
    SR1MUX = 2'bxx;
    ALUK = 2'bxx;
    MIO_EN = 1'b0;
    R_W = 1'bx;

    case (state)
      RESET: begin
        state_next = FETCH;
      end
      FETCH: begin
        state_next = FETCH_MEM;
        LD_MAR = 1'b1;
        GatePC = 1'b1;
        LD_PC = 1'b1;
        PCMUX = 2'b00;
      end
      FETCH_MEM: begin
        state_next = microsequencer_state'((R) ? FETCH_SET_IR : FETCH_MEM);
        LD_MDR = 1'b1;
        MIO_EN = 1'b1;
        R_W = 1'b0;
      end
      FETCH_SET_IR: begin
        state_next = DECODE;
        LD_IR = 1'b1;
        GateMDR = 1'b1;
      end
      DECODE: begin
        case (IR[15:12])
          4'd1: state_next = ADD;
          4'd5: state_next = AND;
          4'd9: state_next = NOT;
          4'd15: state_next = TRAP;
          4'd14: state_next = LEA;
          4'd2: state_next = LD;
          4'd6: state_next = LDR;
          4'd10: state_next = LDI;
          4'd11: state_next = STI;
          4'd7: state_next = STR;
          4'd3: state_next = ST;
          4'd4: state_next = JSR_CHECK;
          4'd12: state_next = JMP;
          4'd0: state_next = BR_CHECK;
        endcase
        LD_BEN = 1'b1;
      end
      ADD: begin
        state_next = FETCH;
        LD_REG = 1'b1;
        LD_CC = 1'b1;
        GateALU = 1'b1;
        DRMUX = 2'b00;
        SR1MUX = 2'b01;
        ALUK = 2'b00;
      end
      AND: begin
        state_next = FETCH;
        LD_REG = 1'b1;
        LD_CC = 1'b1;
        GateALU = 1'b1;
        DRMUX = 2'b00;
        SR1MUX = 2'b01;
        ALUK = 2'b01;
      end
      NOT: begin
        state_next = FETCH;
        LD_REG = 1'b1;
        LD_CC = 1'b1;
        GateALU = 1'b1;
        DRMUX = 2'b00;
        SR1MUX = 2'b01;
        ALUK = 2'b10;
      end
      TRAP: begin
        state_next = microsequencer_state'((IR[7:0] == 8'h25) ? HALT : TRAP_MEM);
        LD_MAR = 1'b1;
        GateMARMUX = 1'b1;
        MARMUX = 1'b0;
      end
      HALT: begin
        $finish;
      end
      TRAP_MEM: begin
        state_next = microsequencer_state'((R) ? TRAP_SET_PC : TRAP_MEM);
        LD_MDR = 1'b1;
        MIO_EN = 1'b1;
        R_W = 1'b0;
        LD_REG = 1'b1;
        DRMUX = 2'b01;
        GatePC = 1'b1;
      end
      TRAP_SET_PC: begin
        state_next = FETCH;
        GateMDR = 1'b1;
        LD_PC = 1'b1;
        PCMUX = 2'b01;
      end
      LEA: begin
        state_next = FETCH;
        LD_REG = 1'b1;
        LD_CC = 1'b1;
        DRMUX = 2'b00;
        GateMARMUX = 1'b1;
        MARMUX = 1'b1;
        ADDR1MUX = 1'b0;
        ADDR2MUX = 2'b10;
      end
      LD: begin
        state_next = LD_MEM;
        LD_MAR = 1'b1;
        GateMARMUX = 1'b1;
        MARMUX = 1'b1;
        ADDR1MUX = 1'b0;
        ADDR2MUX = 2'b10;
      end
      LD_MEM: begin
        state_next = microsequencer_state'((R) ? LD_SET_DR : LD_MEM);
        LD_MDR = 1'b1;
        MIO_EN = 1'b1;
        R_W = 1'b0;
      end
      LD_SET_DR: begin
        state_next = FETCH;
        LD_REG = 1'b1;
        DRMUX = 2'b00;
        GateMDR = 1'b1;
        LD_CC = 1'b1;
      end
      LDR: begin
        state_next = LD_MEM;
        LD_MAR = 1'b1;
        GateMARMUX = 1'b1;
        MARMUX = 1'b1;
        ADDR1MUX = 1'b1;
        ADDR2MUX = 2'b01;
        SR1MUX = 2'b01;
      end
      LDI: begin
        state_next = LDI_MEM;
        LD_MAR = 1'b1;
        GateMARMUX = 1'b1;
        MARMUX = 1'b1;
        ADDR1MUX = 1'b0;
        ADDR2MUX = 2'b10;
      end
      LDI_MEM: begin
        state_next = microsequencer_state'((R) ? LDI_SET_MAR : LDI_MEM);
        LD_MDR = 1'b1;
        MIO_EN = 1'b1;
        R_W = 1'b0;
      end
      LDI_SET_MAR: begin
        state_next = LD_MEM;
        LD_MAR = 1'b1;
        GateMDR = 1'b1;
      end
      ST: begin
        state_next = ST_SET_MDR;
        LD_MAR = 1'b1;
        GateMARMUX = 1'b1;
        MARMUX = 1'b1;
        ADDR1MUX = 1'b0;
        ADDR2MUX = 2'b10;
      end
      ST_SET_MDR: begin
        state_next = ST_MEM;
        LD_MDR = 1;
        GateMARMUX = 1'b1;
        MARMUX = 1'b1;
        ADDR1MUX = 1'b1;
        ADDR2MUX = 2'b00;
        SR1MUX = 2'b00;
      end
      ST_MEM: begin
        state_next = microsequencer_state'((R) ? FETCH : ST_MEM);
        MIO_EN = 1'b1;
        R_W = 1'b1;
      end
      STR: begin
        state_next = ST_SET_MDR;
        LD_MAR = 1'b1;
        GateMARMUX = 1'b1;
        MARMUX = 1'b1;
        ADDR1MUX = 1'b1;
        ADDR2MUX = 2'b01;
        SR1MUX = 2'b01;
      end
      STI: begin
        state_next = STI_MEM;
        LD_MAR = 1'b1;
        GateMARMUX = 1'b1;
        MARMUX = 1'b1;
        ADDR1MUX = 1'b0;
        ADDR2MUX = 2'b10;
      end
      STI_MEM: begin
        state_next = microsequencer_state'((R) ? STI_SET_MAR : STI_MEM);
        LD_MDR = 1'b1;
        MIO_EN = 1'b1;
        R_W = 1'b0;
      end
      STI_SET_MAR: begin
        state_next = ST_SET_MDR;
        LD_MAR = 1'b1;
        GateMDR = 1'b1;
      end
      JSR_CHECK: begin
        state_next = microsequencer_state'((IR[11]) ? JSR : JSRR);
        LD_REG = 1'b1;
        DRMUX = 2'b01;
        GatePC = 1'b1;
      end
      JSR: begin
        state_next = FETCH;
        LD_PC = 1'b1;
        GateMARMUX = 1'b1;
        MARMUX = 1'b1;
        ADDR1MUX = 1'b0;
        ADDR2MUX = 2'b11;
        PCMUX = 2'b01;
      end
      JSRR: begin
        state_next = FETCH;
        LD_PC = 1'b1;
        GateMARMUX = 1'b1;
        MARMUX = 1'b1;
        ADDR1MUX = 1'b1;
        ADDR2MUX = 2'b00;
        SR1MUX = 2'b01;
        PCMUX = 2'b01;
      end
      JMP: begin
        state_next = FETCH;
        LD_PC = 1'b1;
        GateMARMUX = 1'b1;
        MARMUX = 1'b1;
        ADDR1MUX = 1'b1;
        ADDR2MUX = 2'b00;
        SR1MUX = 2'b01;
        PCMUX = 2'b01;
      end
      BR_CHECK: begin
        state_next = microsequencer_state'((BEN) ? BR : FETCH);
      end
      BR: begin
        state_next = FETCH;
        LD_PC = 1'b1;
        GateMARMUX = 1'b1;
        MARMUX = 1'b1;
        ADDR1MUX = 1'b0;
        ADDR2MUX = 2'b10;
        PCMUX = 2'b01;
      end
    endcase
  end

  always @(posedge clk) begin
    if (!rstn) state <= RESET;
    else state <= state_next;
  end
endmodule

module datapath_memory (
  input clk,
  input rstn,
  input [15:0] bus,

  input LD_MAR,
  input LD_MDR,
  input MIO_EN,
  input R_W,

  output reg R,
  output reg [15:0] MAR,
  output reg [15:0] MDR
);
  reg [15:0] MEMout;

  reg [15:0] MEM [0:65535];

  initial begin
      for (int i = 0; i < 65536; i++) MEM[i] = 16'b0;
      $readmemb("lc3mem.bin", MEM, 0, 22);
      $readmemb("array_10.bin", MEM, 256, 267);
      $readmemb("array_x.bin", MEM, 512, 533);
  end

  always @(*) begin
    R = 1'b1;
    if (!rstn) begin
      MAR = 16'b0;
      MDR = 16'b0;
    end
    else begin
      if (LD_MAR) MAR = bus;
      if (MIO_EN) begin
        // Write
        if (R_W) MEM[MAR] = MDR;
        // Read
        else MEMout = MEM[MAR];
      end
      if (LD_MDR) MDR = (MIO_EN) ? MEMout : bus;
    end
  end
endmodule

module BEN_CC (
  input clk,
  input rstn,
  input [15:0] bus,
  input [15:0] IR,

  input reg LD_BEN,
  input reg LD_CC,

  output reg BEN,
  output reg [2:0] CC
);

wire CC_N;
wire CC_Z;
wire CC_P;
wire [2:0] CC_calc;
wire BEN_calc;

// CC Calculations
assign CC_N = bus[15];
assign CC_Z = ~(|bus);
assign CC_P = ~(CC_N | CC_Z);
assign CC_calc = {CC_N, CC_Z, CC_P};

assign BEN_calc = (IR[11] & CC[2]) | (IR[10] & CC[1]) | (IR[9] & CC[0]);

always @(posedge clk) begin
  if (!rstn) begin
    CC <= 3'b0;
    BEN <= 1'b0;
  end
  else begin 
    if (LD_CC) CC <= CC_calc;
    if (LD_BEN) BEN <= BEN_calc;
  end
end

endmodule

module pc_mar_muxes (
  input clk,
  input rstn,
  input MARMUX,
  input [1:0] ADDR2MUX,
  input ADDR1MUX,
  input [1:0] PCMUX,
  input LD_PC,
  input [15:0] IR,
  input [15:0] SR1OUT,
  input [15:0] bus,
  output reg [15:0] MARMUXout,
  output [15:0] PCout
);
  reg [15:0] ADDER_ADDR1;
  reg [15:0] ADDER_ADDR2;
  wire [15:0] ADDER_OUT;
  reg [15:0] PC_IN;
  wire [15:0] PC;

  reg_16 PC_REG (clk, rstn, LD_PC, PC_IN, PC);

  assign ADDER_OUT = ADDER_ADDR1 + ADDER_ADDR2;
  assign PCout = PC;

  always @(*) begin
    case (ADDR1MUX)
      1'b0: ADDER_ADDR1 = PC;
      1'b1: ADDER_ADDR1 = SR1OUT;
    endcase
    case (ADDR2MUX)
      2'b00: ADDER_ADDR2 = 16'b0;
      2'b01: ADDER_ADDR2 = {{10{IR[5]}}, IR[5:0]};
      2'b10: ADDER_ADDR2 = {{7{IR[8]}}, IR[8:0]};
      2'b11: ADDER_ADDR2 = {{5{IR[10]}}, IR[10:0]};
    endcase
    case (PCMUX)
      2'b00: PC_IN = PC + 1'd1;
      2'b01: PC_IN = bus;
      2'b10: PC_IN = ADDER_OUT;
    endcase
    case (MARMUX)
      1'b0: MARMUXout = {8'b0, IR[7:0]};
      1'b1: MARMUXout = ADDER_OUT;
    endcase
  end

endmodule


module alu(
  input [15:0] A,
  input [15:0] B,
  input [1:0] ALUK,
  output reg [15:0] out
);

  always @(*) begin
    case (ALUK)
      2'b00: out = A + B;
      2'b01: out = A & B;
      2'b10: out = ~A;
      2'b11: out = A;
    endcase
  end

endmodule

module regfile(
    input clk,
    input rstn,
    input [15:0] DRIN,
    input [2:0] DR,
    input [2:0] SR1,
    input [2:0] SR2,
    input LD,
    output reg [15:0] SR1OUT,
    output reg [15:0] SR2OUT
);
    reg [7:0] loads;
    reg [15:0] outs [7:0];
    
    reg_16 R0 (clk, rstn, loads[0], DRIN, outs[0]);
    reg_16 R1 (clk, rstn, loads[1], DRIN, outs[1]);
    reg_16 R2 (clk, rstn, loads[2], DRIN, outs[2]);
    reg_16 R3 (clk, rstn, loads[3], DRIN, outs[3]);
    reg_16 R4 (clk, rstn, loads[4], DRIN, outs[4]);
    reg_16 R5 (clk, rstn, loads[5], DRIN, outs[5]);
    reg_16 R6 (clk, rstn, loads[6], DRIN, outs[6]);
    reg_16 R7 (clk, rstn, loads[7], DRIN, outs[7]);
    
    always @(*) begin
        loads = 8'b0;
        if (LD) loads[DR] = 1'b1;
        SR1OUT = outs[SR1];
        SR2OUT = outs[SR2];
    end
    
endmodule

module reg_16(
    input clk,
    input rstn,
    input load,
    input [15:0] wdata,
    output reg [15:0] out
);

    always @(posedge clk) begin
        if (!rstn) out <= 16'b0;
        else begin
            if (load) out <= wdata;
            else out <= out;
        end
    end

endmodule

testbench.v
module tb ();
    reg clk;
    reg rstn;
    reg [15:0] bus;

  	datapath datapath1 (clk, rstn, bus);

    always #10 clk = ~clk;

    initial begin
      $dumpfile("dump.vcd");
      $dumpvars(0, tb);
    end


    initial begin
        clk = 0;
        rstn = 0;
      
        #20 rstn = 1;
    end

endmodule

dump.vcd
$date
	Tue Dec 23 16:06:23 2025
$end
$version
	Icarus Verilog
$end
$timescale
	1s
$end
$scope module tb $end
$var wire 16 ! bus [15:0] $end
$var reg 1 " clk $end
$var reg 1 # rstn $end
$scope module datapath1 $end
$var wire 16 $ ALUA [15:0] $end
$var wire 16 % DRIN [15:0] $end
$var wire 1 " clk $end
$var wire 1 # rstn $end
$var wire 16 & SR2OUT [15:0] $end
$var wire 3 ' SR2 [2:0] $end
$var wire 16 ( SR1OUT [15:0] $end
$var wire 2 ) SR1MUX [1:0] $end
$var wire 1 * R_W $end
$var wire 1 + R $end
$var wire 16 , PCout [15:0] $end
$var wire 2 - PCMUX [1:0] $end
$var wire 1 . MIO_EN $end
$var wire 16 / MDRout [15:0] $end
$var wire 16 0 MARout [15:0] $end
$var wire 16 1 MARMUXout [15:0] $end
$var wire 1 2 MARMUX $end
$var wire 1 3 LD_REG $end
$var wire 1 4 LD_PC $end
$var wire 1 5 LD_MDR $end
$var wire 1 6 LD_MAR $end
$var wire 1 7 LD_IR $end
$var wire 1 8 LD_CC $end
$var wire 1 9 LD_BEN $end
$var wire 1 : GatePC $end
$var wire 1 ; GateMDR $end
$var wire 1 < GateMARMUX $end
$var wire 1 = GateALU $end
$var wire 2 > DRMUX [1:0] $end
$var wire 3 ? CC [2:0] $end
$var wire 1 @ BEN $end
$var wire 16 A ALUout [15:0] $end
$var wire 2 B ALUK [1:0] $end
$var wire 16 C ALUB [15:0] $end
$var wire 2 D ADDR2MUX [1:0] $end
$var wire 1 E ADDR1MUX $end
$var reg 3 F DR [2:0] $end
$var reg 16 G IR [15:0] $end
$var reg 3 H SR1 [2:0] $end
$var reg 16 I bus [15:0] $end
$scope module BEN_CC1 $end
$var wire 1 J BEN_calc $end
$var wire 1 K CC_P $end
$var wire 1 L CC_Z $end
$var wire 16 M IR [15:0] $end
$var wire 16 N bus [15:0] $end
$var wire 1 " clk $end
$var wire 1 # rstn $end
$var wire 1 8 LD_CC $end
$var wire 1 9 LD_BEN $end
$var wire 3 O CC_calc [2:0] $end
$var wire 1 P CC_N $end
$var reg 1 @ BEN $end
$var reg 3 Q CC [2:0] $end
$upscope $end
$scope module alu1 $end
$var wire 16 R A [15:0] $end
$var wire 16 S B [15:0] $end
$var wire 2 T ALUK [1:0] $end
$var reg 16 U out [15:0] $end
$upscope $end
$scope module control_unit1 $end
$var wire 1 @ BEN $end
$var wire 16 V IR [15:0] $end
$var wire 1 " clk $end
$var wire 1 # rstn $end
$var wire 1 + R $end
$var reg 1 E ADDR1MUX $end
$var reg 2 W ADDR2MUX [1:0] $end
$var reg 2 X ALUK [1:0] $end
$var reg 2 Y DRMUX [1:0] $end
$var reg 1 = GateALU $end
$var reg 1 < GateMARMUX $end
$var reg 1 ; GateMDR $end
$var reg 1 : GatePC $end
$var reg 1 9 LD_BEN $end
$var reg 1 8 LD_CC $end
$var reg 1 7 LD_IR $end
$var reg 1 6 LD_MAR $end
$var reg 1 5 LD_MDR $end
$var reg 1 4 LD_PC $end
$var reg 1 3 LD_REG $end
$var reg 1 2 MARMUX $end
$var reg 1 . MIO_EN $end
$var reg 2 Z PCMUX [1:0] $end
$var reg 1 * R_W $end
$var reg 2 [ SR1MUX [1:0] $end
$var integer 32 \ state [31:0] $end
$var integer 32 ] state_next [31:0] $end
$upscope $end
$scope module datapath_memory1 $end
$var wire 1 6 LD_MAR $end
$var wire 1 5 LD_MDR $end
$var wire 1 . MIO_EN $end
$var wire 1 * R_W $end
$var wire 16 ^ bus [15:0] $end
$var wire 1 " clk $end
$var wire 1 # rstn $end
$var reg 16 _ MAR [15:0] $end
$var reg 16 ` MDR [15:0] $end
$var reg 16 a MEMout [15:0] $end
$var reg 1 + R $end
$scope begin $ivl_for_loop0 $end
$var integer 32 b i [31:0] $end
$upscope $end
$upscope $end
$scope module pc_mar_muxes1 $end
$var wire 1 E ADDR1MUX $end
$var wire 2 c ADDR2MUX [1:0] $end
$var wire 16 d IR [15:0] $end
$var wire 1 4 LD_PC $end
$var wire 1 2 MARMUX $end
$var wire 2 e PCMUX [1:0] $end
$var wire 16 f PCout [15:0] $end
$var wire 16 g bus [15:0] $end
$var wire 1 " clk $end
$var wire 1 # rstn $end
$var wire 16 h SR1OUT [15:0] $end
$var wire 16 i PC [15:0] $end
$var wire 16 j ADDER_OUT [15:0] $end
$var reg 16 k ADDER_ADDR1 [15:0] $end
$var reg 16 l ADDER_ADDR2 [15:0] $end
$var reg 16 m MARMUXout [15:0] $end
$var reg 16 n PC_IN [15:0] $end
$scope module PC_REG $end
$var wire 1 " clk $end
$var wire 1 4 load $end
$var wire 1 # rstn $end
$var wire 16 o wdata [15:0] $end
$var reg 16 p out [15:0] $end
$upscope $end
$upscope $end
$scope module regfile1 $end
$var wire 3 q DR [2:0] $end
$var wire 16 r DRIN [15:0] $end
$var wire 1 3 LD $end
$var wire 3 s SR1 [2:0] $end
$var wire 3 t SR2 [2:0] $end
$var wire 1 " clk $end
$var wire 1 # rstn $end
$var reg 16 u SR1OUT [15:0] $end
$var reg 16 v SR2OUT [15:0] $end
$var reg 8 w loads [7:0] $end
$scope module R0 $end
$var wire 1 " clk $end
$var wire 1 x load $end
$var wire 1 # rstn $end
$var wire 16 y wdata [15:0] $end
$var reg 16 z out [15:0] $end
$upscope $end
$scope module R1 $end
$var wire 1 " clk $end
$var wire 1 { load $end
$var wire 1 # rstn $end
$var wire 16 | wdata [15:0] $end
$var reg 16 } out [15:0] $end
$upscope $end
$scope module R2 $end
$var wire 1 " clk $end
$var wire 1 ~ load $end
$var wire 1 # rstn $end
$var wire 16 !" wdata [15:0] $end
$var reg 16 "" out [15:0] $end
$upscope $end
$scope module R3 $end
$var wire 1 " clk $end
$var wire 1 #" load $end
$var wire 1 # rstn $end
$var wire 16 $" wdata [15:0] $end
$var reg 16 %" out [15:0] $end
$upscope $end
$scope module R4 $end
$var wire 1 " clk $end
$var wire 1 &" load $end
$var wire 1 # rstn $end
$var wire 16 '" wdata [15:0] $end
$var reg 16 (" out [15:0] $end
$upscope $end
$scope module R5 $end
$var wire 1 " clk $end
$var wire 1 )" load $end
$var wire 1 # rstn $end
$var wire 16 *" wdata [15:0] $end
$var reg 16 +" out [15:0] $end
$upscope $end
$scope module R6 $end
$var wire 1 " clk $end
$var wire 1 ," load $end
$var wire 1 # rstn $end
$var wire 16 -" wdata [15:0] $end
$var reg 16 ." out [15:0] $end
$upscope $end
$scope module R7 $end
$var wire 1 " clk $end
$var wire 1 /" load $end
$var wire 1 # rstn $end
$var wire 16 0" wdata [15:0] $end
$var reg 16 1" out [15:0] $end
$upscope $end
$upscope $end
$upscope $end
$upscope $end
$enddefinitions $end
$comment Show the parameter values. $end
$dumpall
$end
#0
$dumpvars
bx 1"
bx 0"
0/"
bx ."
bx -"
0,"
bx +"
bx *"
0)"
bx ("
bx '"
0&"
bx %"
bx $"
0#"
bx ""
bx !"
0~
bx }
bx |
0{
bx z
bx y
0x
b0 w
bx v
bx u
bx t
bx s
bx r
bx q
bx p
bx o
bx n
bx m
bx l
bx k
bx j
bx i
bx h
bx g
bx f
bx e
bx d
bx c
b10000000000000000 b
bx a
b0 `
b0 _
bx ^
b11011 ]
b0 \
b1 [
bx Z
b0 Y
b0 X
bx W
bx V
bx U
b0 T
bx S
bx R
bx Q
xP
bx O
bx N
bx M
xL
xK
xJ
bx I
bx H
bx G
bx F
xE
bx D
bx C
b0 B
bx A
x@
bx ?
b0 >
1=
0<
0;
0:
09
18
07
06
05
04
13
x2
bx 1
b0 0
b0 /
0.
bx -
bx ,
1+
x*
b1 )
bx (
bx '
bx &
bx %
bx $
0#
0"
bx !
$end
#10
0J
b0 C
b0 S
b0 &
b0 v
b0 $
b0 R
b0 (
b0 h
b0 u
b0 '
b0 t
bx B
bx T
bx X
bx )
bx [
bx >
bx Y
0=
08
03
b0 H
b0 s
b0 F
b0 q
b0 z
b0 }
b0 ""
b0 %"
b0 ("
b0 +"
b0 ."
b0 1"
b0 ,
b0 f
b0 i
b0 p
b11111 \
0@
b0 ?
b0 Q
b0 G
b0 M
b0 V
b0 d
1"
#20
0"
1#
#30
0K
0P
b10 O
1L
b1 n
b1 o
b0 %
b0 r
b0 y
b0 |
b0 !"
b0 $"
b0 '"
b0 *"
b0 -"
b0 0"
b0 !
b0 I
b0 N
b0 ^
b0 g
b0 0
b0 _
b0 -
b0 Z
b0 e
14
1:
16
b11100 ]
b11011 \
1"
#40
0"
#50
b10100000010011 /
b10100000010011 `
b10100000010011 a
0*
1.
15
b11101 ]
bx -
bx Z
bx e
0:
04
06
b1 ,
b1 f
b1 i
b1 p
b11100 \
1"
#60
0"
#70
1K
b1 O
0L
b10100000010011 %
b10100000010011 r
b10100000010011 y
b10100000010011 |
b10100000010011 !"
b10100000010011 $"
b10100000010011 '"
b10100000010011 *"
b10100000010011 -"
b10100000010011 0"
b10100000010011 !
b10100000010011 I
b10100000010011 N
b10100000010011 ^
b10100000010011 g
1;
17
b11110 ]
x*
0.
05
b11101 \
1"
#80
0"
#90
b11 '
b11 t
19
b111 ]
0;
07
b11110 \
b10100000010011 G
b10100000010011 M
b10100000010011 V
b10100000010011 d
1"
#100
0"
#110
1K
0P
b1 O
0L
b10100 1
b10100 m
b10100 j
b10011 l
b1 k
b10100 %
b10100 r
b10100 y
b10100 |
b10100 !"
b10100 $"
b10100 '"
b10100 *"
b10100 -"
b10100 0"
b10100 !
b10100 I
b10100 N
b10100 ^
b10100 g
b10100 0
b10100 _
b10 D
b10 W
b10 c
0E
12
1<
16
b1000 ]
09
b111 \
1"
#120
0"
#130
b111111111 /
b111111111 `
b111111111 a
0*
1.
15
b1001 ]
bx D
bx W
bx c
xE
x2
0<
06
b1000 \
1"
#140
0"
#150
1&"
0x
b111111111 %
b111111111 r
b111111111 y
b111111111 |
b111111111 !"
b111111111 $"
b111111111 '"
b111111111 *"
b111111111 -"
b111111111 0"
b111111111 !
b111111111 I
b111111111 N
b111111111 ^
b111111111 g
b100 F
b100 q
b10000 w
18
1;
b0 >
b0 Y
13
b11011 ]
x*
0.
05
b1001 \
1"
#160
0"
#170
0&"
b10 n
b10 o
b1 0
b1 _
b1 %
b1 r
b1 y
b1 |
b1 !"
b1 $"
b1 '"
b1 *"
b1 -"
b1 0"
b1 !
b1 I
b1 N
b1 ^
b1 g
b0 w
b0 -
b0 Z
b0 e
14
1:
16
b11100 ]
bx >
bx Y
0;
08
03
b111111111 ("
b11011 \
b1 ?
b1 Q
1"
#180
0"
#190
b101110110100000 /
b101110110100000 `
b101110110100000 a
0*
1.
15
b11101 ]
bx -
bx Z
bx e
0:
04
06
b11 n
b11 o
b10 %
b10 r
b10 y
b10 |
b10 !"
b10 $"
b10 '"
b10 *"
b10 -"
b10 0"
b10 !
b10 I
b10 N
b10 ^
b10 g
b11100 \
b10 ,
b10 f
b10 i
b10 p
1"
#200
0"
#210
b101110110100000 %
b101110110100000 r
b101110110100000 y
b101110110100000 |
b101110110100000 !"
b101110110100000 $"
b101110110100000 '"
b101110110100000 *"
b101110110100000 -"
b101110110100000 0"
b101110110100000 !
b101110110100000 I
b101110110100000 N
b101110110100000 ^
b101110110100000 g
1;
17
b11110 ]
x*
0.
05
b11101 \
1"
#220
0"
#230
b0 '
b0 t
19
b1 ]
0;
07
b101110110100000 G
b101110110100000 M
b101110110100000 V
b101110110100000 d
b11110 \
1"
#240
0"
#250
0K
1,"
0P
b10 O
1L
0&"
b0 A
b0 U
b0 %
b0 r
b0 y
b0 |
b0 !"
b0 $"
b0 '"
b0 *"
b0 -"
b0 0"
b0 !
b0 I
b0 N
b0 ^
b0 g
b110 H
b110 s
b110 F
b110 q
b1000000 w
b1 B
b1 T
b1 X
b1 )
b1 [
b0 >
b0 Y
1=
18
13
b11011 ]
09
b1 \
1"
#260
0"
#270
1K
1J
b1 O
0L
0,"
b10 0
b10 _
b10 %
b10 r
b10 y
b10 |
b10 !"
b10 $"
b10 '"
b10 *"
b10 -"
b10 0"
b10 !
b10 I
b10 N
b10 ^
b10 g
b0 w
b0 -
b0 Z
b0 e
14
1:
16
b11100 ]
bx B
bx T
bx X
bx )
bx [
bx >
bx Y
0=
08
03
b10 ?
b10 Q
b11011 \
1"
#280
0"
#290
b101011011100000 /
b101011011100000 `
b101011011100000 a
0*
1.
15
b11101 ]
bx -
bx Z
bx e
0:
04
06
b11 ,
b11 f
b11 i
b11 p
b11100 \
1"
#300
0"
#310
b101011011100000 %
b101011011100000 r
b101011011100000 y
b101011011100000 |
b101011011100000 !"
b101011011100000 $"
b101011011100000 '"
b101011011100000 *"
b101011011100000 -"
b101011011100000 0"
b101011011100000 !
b101011011100000 I
b101011011100000 N
b101011011100000 ^
b101011011100000 g
1;
17
b11110 ]
x*
0.
05
b11101 \
1"
#320
0"
#330
19
b1 ]
0;
07
b11110 \
b101011011100000 G
b101011011100000 M
b101011011100000 V
b101011011100000 d
1"
#340
0"
#350
0K
1#"
b10 O
1L
0,"
b0 %
b0 r
b0 y
b0 |
b0 !"
b0 $"
b0 '"
b0 *"
b0 -"
b0 0"
b0 !
b0 I
b0 N
b0 ^
b0 g
b11 H
b11 s
b11 F
b11 q
b1000 w
b1 B
b1 T
b1 X
b1 )
b1 [
b0 >
b0 Y
1=
18
13
b11011 ]
09
1@
b1 \
1"
#360
0"
#370
1K
b1 O
0L
0#"
b100 n
b100 o
b11 0
b11 _
b11 %
b11 r
b11 y
b11 |
b11 !"
b11 $"
b11 '"
b11 *"
b11 -"
b11 0"
b11 !
b11 I
b11 N
b11 ^
b11 g
b0 w
b0 -
b0 Z
b0 e
14
1:
16
b11100 ]
bx B
bx T
bx X
bx )
bx [
bx >
bx Y
0=
08
03
b11011 \
1"
#380
0"
